CHANGELOG.txt
LICENCE.txt
MANIFEST.in
README.txt
setup.py
Open_CAMERA.egg-info/PKG-INFO
Open_CAMERA.egg-info/SOURCES.txt
Open_CAMERA.egg-info/dependency_links.txt
Open_CAMERA.egg-info/requires.txt
Open_CAMERA.egg-info/top_level.txt
Open_camera/__init__.py